webdrivermanager_cn/__init__.py
webdrivermanager_cn/chrome.py
webdrivermanager_cn/geckodriver.py
webdrivermanager_cn/version.py
webdrivermanager_cn/core/__init__.py
webdrivermanager_cn/core/cache_manager.py
webdrivermanager_cn/core/config.py
webdrivermanager_cn/core/download_manager.py
webdrivermanager_cn/core/driver.py
webdrivermanager_cn/core/file_manager.py
webdrivermanager_cn/core/log_manager.py
webdrivermanager_cn/core/mirror_manager.py
webdrivermanager_cn/core/mirror_urls.py
webdrivermanager_cn/core/mixin.py
webdrivermanager_cn/core/os_manager.py
webdrivermanager_cn/core/request.py
webdrivermanager_cn/core/time_.py
webdrivermanager_cn/core/version_manager.py
webdrivermanager_cn/driver/__init__.py
webdrivermanager_cn/driver/chrome.py
webdrivermanager_cn/driver/geckodriver.py
webdrivermanager_cn-2.4.2.dist-info/licenses/LICENSE
webdrivermanager_cn-2.4.2.dist-info/METADATA
webdrivermanager_cn-2.4.2.dist-info/WHEEL
webdrivermanager_cn-2.4.2.dist-info/top_level.txt
webdrivermanager_cn-2.4.2.dist-info/RECORD
