Metadata-Version: 2.4
Name: webdrivermanager_cn
Version: 2.4.2
Summary: 基于阿里源开发的WebDriver管理工具
Home-page: https://gitee.com/Joker_JH/webdrivermanagercn
Author: 御风
Author-email: eternallyyf@163.com
License: Apache License 2.0
Requires-Python: >=3.7
License-File: LICENSE
Requires-Dist: requests
Requires-Dist: packaging
Requires-Dist: filelock==3.18.0
Dynamic: author
Dynamic: author-email
Dynamic: description
Dynamic: description-content-type
Dynamic: home-page
Dynamic: license
Dynamic: license-file
Dynamic: requires-dist
Dynamic: requires-python
Dynamic: summary
